{
  "SM_Clay": "clay",
  "SM_Juniper_Berry_01": "berry_alpine_juniper",
  "SM_Blackberry_05": "berry_blackberries",
  "SM_Blueberry_05": "berry_blueberries",
  "SM_Cloudberry_01_Plant": "berry_cloudberry",
  "SM_Elderberry_Var10": "berry_elderberries",
  "SM_Gooseberry_01": "berry_gooseberry",
  "SM_Grapes_01": "berry_grapevines",
  "SM_Hawthorne_Berry_01": "berry_hawthorne",
  "SM_Pineberry": "berry_pineberry",
  "SM_Raspberry_08": "berry_raspberries",
  "SM_Redcurrant_02": "berry_red_currant",
  "SM_Rose_Hip_Var07": "berry_rosehips",
  "SM_Strawberry": "berry_strawberry",
  "SM_Starworth_Var4": "bushy_starworth",
  "SM_Castor_V2": "castor_plant",
  "SM_Alfalfa_var02": "flower_alfalfa",
  "SM_Bat_Flower_01": "flower_batflower",
  "SM_Californian_Poppy_Var3": "flower_californianpoppy",
  "SM_Bladder_Campion_Var05": "flower_campion",
  "SM_Crane_Flower_Var08": "flower_crane",
  "SM_Daisy_V1": "flower_daisy",
  "SM_Dandelion_02": "flower_dandelion",
  "SM_Datura_Med_01": "flower_datura",
  "SM_Nightshade_Small_01": "flower_deadly_nightshade",
  "SM_High_Mallow_var2": "flower_highmallow",
  "SM_Lavender_01": "flower_lavender",
  "SM_Purpletop_Vervain_01": "flower_loios_tears",
  "SM_Pasque_Flower_Var06": "flower_pasque",
  "SM_Periwinkle_V1": "flower_periwinkle",
  "SM_Plantago_var1": "flower_plantago",
  "SM_Rain_Lily_Var2": "flower_rain_lily",
  "SM_Red_Poppy": "flower_redpoppy",
  "SM_Soapwort_v1": "flower_soapwort",
  "SM_Tansy_var2": "flower_tansy",
  "SM_Wolfsbane_M_02": "flower_wolfsbane",
  "SM_AppleTreeSmall_Red": "fruit_apple_red",
  "SM_Barley_01": "grass_barley",
  "SM_Catgrass_Var01": "grass_catgrass",
  "SM_Cotton_Var09": "grass_cotton",
  "SM_Flax_01": "grass_flax",
  "SM_Hemp_01": "grass_hemp",
  "SM_Oat_01": "grass_oat",
  "SM_Reeds_02": "grass_reeds",
  "SM_Rye_03": "grass_rye",
  "SM_Sugarcane_03": "grass_sugarcane",
  "SM_Wheat_V2": "grass_wheat",
  "SM_Angelica_01": "herb_angelica",
  "SM_Chives_Var07": "herb_chives",
  "SM_Crownbeard_03": "herb_crown_beard",
  "SM_Fennel_01": "herb_fennel",
  "SM_Garlic_01": "herb_garlic",
  "SM_Lemongrass_Var05": "herb_lemongrass",
  "SM_Lily_Of_The_Valley_Var02": "herb_lily",
  "SM_Meadowsweet_01": "herb_meadowsweet",
  "SM_Mustard_Var3": "herb_mustard",
  "SM_Parsley_01": "herb_parsley",
  "SM_Rosemary_Var01": "herb_rosemary",
  "SM_Sage_V1": "herb_sage",
  "SM_Sow_Thistle_V4": "herb_sowthistle",
  "SM_Thyme_Var07": "herb_thyme",
  "SM_WaterCress_Var02": "herb_watercress",
  "SM_HopBush_01": "hops",
  "SM_Amanita_Regalis_06": "mushroom_amanitaregalis",
  "SM_Berserker_02": "mushroom_berserker",
  "SM_Chanterelli_11": "mushroom_chanterelle",
  "SM_Chlorine_Lepidella_04": "mushroom_chlorine",
  "SM_Dapperling_01": "mushroom_dapperling",
  "SM_Death_Cap_01": "mushroom_death_cap",
  "SM_Cremini_01": "mushroom_divine",
  "SM_Enoki_01": "mushroom_enoki",
  "SM_Fools_Webcap_01": "mushroom_fools_webcap",
  "SM_Morel_01": "mushroom_morels",
  "SM_Oyster_Mushroom_01": "mushroom_oyster_mushrooms",
  "SM_Penny_Bun_01": "mushroom_pennybun",
  "SM_Porcini_01": "mushroom_porcini",
  "SM_Galerina_Marginata_01": "mushroom_skullcap",
  "SM_Elegant_Stinkhorn_01": "mushroom_stinkhorn",
  "SM_Black_Trumpet_01": "mushroom_trumpets",
  "SM_OnionPlant_Red": "onion_red",
  "SM_OnionPlant_Yellow": "onion_yellow",
  "SM_Branch_01": "tree_branch",
  "SM_Flint_04": "flint_stones",
  "SM_Gneiss_02": "gneiss_stones",
  "SM_Granite_01": "granite_stones",
  "SM_Limestone_01": "lime_stone_stones",
  "SM_Pumice": "volcanic_rock_stones",
  "SM_Granite_Deposit_01_Copper": "copper_deposit",
  "SM_Gneiss_Deposit_01": "gneiss_deposit",
  "SM_Granite_Deposit_01": "granite_deposit",
  "SM_Granite_Deposit_01_Iron_Pure": "iron_deposit",
  "SM_Granite_Deposit_01_Iron_Impure": "iron_deposit_impure",
  "SM_Limestone_Deposit_01": "limestone_deposit",
  "SM_Granite_Deposit_01_Tin": "tin_deposit",
  "PD_NPC_Animal_Badger_T2": "PD_NPC_Animal_Badger_T2",
  "PD_NPC_Animal_Bear_T18": "PD_NPC_Animal_Bear_T18",
  "PD_NPC_Animal_Bear_T24": "PD_NPC_Animal_Bear_T24",
  "PD_NPC_Animal_Bear_T32": "PD_NPC_Animal_Bear_T32",
  "PD_NPC_Animal_Boar_T12": "PD_NPC_Animal_Boar_T12",
  "PD_NPC_Animal_Boar_T3": "PD_NPC_Animal_Boar_T3",
  "PD_NPC_Animal_Boar_T5": "PD_NPC_Animal_Boar_T5",
  "PD_NPC_Animal_Deer_Stag_T3": "PD_NPC_Animal_Deer_Stag_T3",
  "PD_NPC_Animal_Deer_T2": "PD_NPC_Animal_Deer_T2",
  "PD_NPC_Animal_Fox_T1": "PD_NPC_Animal_Fox_T1",
  "PD_NPC_Animal_Frog_T1": "PD_NPC_Animal_Frog_T1",
  "PD_NPC_Animal_Lizard_T1": "PD_NPC_Animal_Lizard_T1",
  "PD_NPC_Animal_Rabbit_T1": "PD_NPC_Animal_Rabbit_T1",
  "PD_NPC_Animal_Wolf_T10": "PD_NPC_Animal_Wolf_T10",
  "PD_NPC_Animal_Wolf_T16": "PD_NPC_Animal_Wolf_T16",
  "PD_NPC_Animal_Wolf_T6": "PD_NPC_Animal_Wolf_T6",
  "PD_NPC_Animal_Wolf_T16_Bonebreaker": "PD_NPC_Animal_Wolf_T16_Bonebreaker",
  "PD_NPC_Animal_Wolf_T16_Old_Fang": "PD_NPC_Animal_Wolf_T16_Old_Fang",
  "PD_NPC_Animal_Wolf_T18_Curse_of_the_Vale": "PD_NPC_Animal_Wolf_T18_Curse_of_the_Vale",
  "PD_NPC_Animal_Wolf_T18_Luna_Wolf": "PD_NPC_Animal_Wolf_T18_Luna_Wolf",
  "PD_NPC_Animal_Wolf_T18_Wolf_Elder": "PD_NPC_Animal_Wolf_T18_Wolf_Elder",
  "PD_NPC_Animal_Wolf_T23_Mothers_Bane": "PD_NPC_Animal_Wolf_T23_Mothers_Bane",
  "PD_NPC_Animal_Wolf_T23_Night_Terror": "PD_NPC_Animal_Wolf_T23_Night_Terror",
  "PD_NPC_Cor_Bear_T54": "PD_NPC_Cor_Bear_T54",
  "PD_NPC_Cor_Boar_T16": "PD_NPC_Cor_Boar_T16",
  "PD_NPC_Cor_Boar_T30": "PD_NPC_Cor_Boar_T30",
  "PD_NPC_Cor_Boar_T42": "PD_NPC_Cor_Boar_T42",
  "PD_NPC_Cor_Wolf_T42": "PD_NPC_Cor_Wolf_T42",
  "PD_NPC_Cor_Boar_T23_Infested_Vector": "PD_NPC_Cor_Boar_T23_Infested_Vector",
  "PD_NPC_Cor_Boar_T25_Fetid_Vector": "PD_NPC_Cor_Boar_T25_Fetid_Vector",
  "PD_NPC_Cor_Boar_T27_Toxic_Vector": "PD_NPC_Cor_Boar_T27_Toxic_Vector",
  "PD_NPC_Cor_Boar_T34_Bott_Carrier": "PD_NPC_Cor_Boar_T34_Bott_Carrier",
  "PD_NPC_Cor_Boar_T36_Aper_Alpha": "PD_NPC_Cor_Boar_T36_Aper_Alpha",
  "PD_NPC_Cor_Boar_T36_Blighted_Pet": "PD_NPC_Cor_Boar_T36_Blighted_Pet",
  "PD_NPC_Cor_Boar_T40_Bedlam": "PD_NPC_Cor_Boar_T40_Bedlam",
  "PD_NPC_Cor_Boar_T40_Fresh_Meat": "PD_NPC_Cor_Boar_T40_Fresh_Meat",
  "PD_NPC_Cor_Boar_T40_Squalor": "PD_NPC_Cor_Boar_T40_Squalor",
  "PD_NPC_Cor_Boar_T50_Aper_Magnus": "PD_NPC_Cor_Boar_T50_Aper_Magnus",
  "PD_NPC_Cor_Boar_T50_Precious_Carrier": "PD_NPC_Cor_Boar_T50_Precious_Carrier",
  "PD_NPC_Cor_Boar_T50_Shadow_of_Nago": "PD_NPC_Cor_Boar_T50_Shadow_of_Nago",
  "PD_NPC_Cor_Boar_T52_Aper_Maximus": "PD_NPC_Cor_Boar_T52_Aper_Maximus",
  "PD_NPC_Zeb_Doctor_T12": "PD_NPC_Zeb_Doctor_T12",
  "PD_NPC_Zeb_Doctor_T16": "PD_NPC_Zeb_Doctor_T16",
  "PD_NPC_Zeb_Doctor_T21": "PD_NPC_Zeb_Doctor_T21",
  "PD_NPC_Zeb_Doctor_T28": "PD_NPC_Zeb_Doctor_T28",
  "PD_NPC_Zeb_Doctor_T33": "PD_NPC_Zeb_Doctor_T33",
  "PD_NPC_Zeb_Doctor_T40": "PD_NPC_Zeb_Doctor_T40",
  "PD_NPC_Zeb_Guardian_T11": "PD_NPC_Zeb_Guardian_T11",
  "PD_NPC_Zeb_Guardian_T14": "PD_NPC_Zeb_Guardian_T14",
  "PD_NPC_Zeb_Guardian_T19": "PD_NPC_Zeb_Guardian_T19",
  "PD_NPC_Zeb_Guardian_T24": "PD_NPC_Zeb_Guardian_T24",
  "PD_NPC_Zeb_Guardian_T30": "PD_NPC_Zeb_Guardian_T30",
  "PD_NPC_Zeb_Guardian_T42": "PD_NPC_Zeb_Guardian_T42",
  "PD_NPC_Zeb_Overseer_T24": "PD_NPC_Zeb_Overseer_T24",
  "PD_NPC_Zeb_Overseer_T38": "PD_NPC_Zeb_Overseer_T38",
  "PD_NPC_Zeb_Warrior_T10": "PD_NPC_Zeb_Warrior_T10",
  "PD_NPC_Zeb_Warrior_T16": "PD_NPC_Zeb_Warrior_T16",
  "PD_NPC_Zeb_Warrior_T18": "PD_NPC_Zeb_Warrior_T18",
  "PD_NPC_Zeb_Warrior_T22": "PD_NPC_Zeb_Warrior_T22",
  "PD_NPC_Zeb_Warrior_T27": "PD_NPC_Zeb_Warrior_T27",
  "PD_NPC_Zeb_Warrior_T31": "PD_NPC_Zeb_Warrior_T31",
  "PD_NPC_Zeb_Warrior_T39": "PD_NPC_Zeb_Warrior_T39",
  "PD_NPC_Zeb_Doctor_T20_Starved_Distortion_Initiate": "PD_NPC_Zeb_Doctor_T20_Starved_Distortion_Initiate",
  "PD_NPC_Zeb_Doctor_T20_Starved_Undeath_Initiate": "PD_NPC_Zeb_Doctor_T20_Starved_Undeath_Initiate",
  "PD_NPC_Zeb_Doctor_T20_Starved_Void_Initiate": "PD_NPC_Zeb_Doctor_T20_Starved_Void_Initiate",
  "PD_NPC_Zeb_Doctor_T21_Zebian_Demoncaller": "PD_NPC_Zeb_Doctor_T21_Zebian_Demoncaller",
  "PD_NPC_Zeb_Doctor_T34_Servant_of_the_Pound": "PD_NPC_Zeb_Doctor_T34_Servant_of_the_Pound",
  "PD_NPC_Zeb_Doctor_T35_Priest_of_Zeb": "PD_NPC_Zeb_Doctor_T35_Priest_of_Zeb",
  "PD_NPC_Zeb_Guardian_T20_Counter_of_Flies": "PD_NPC_Zeb_Guardian_T20_Counter_of_Flies",
  "PD_NPC_Zeb_Guardian_T20_Hivetender": "PD_NPC_Zeb_Guardian_T20_Hivetender",
  "PD_NPC_Zeb_Guardian_T20_Zebian_Camp_Leader": "PD_NPC_Zeb_Guardian_T20_Zebian_Camp_Leader",
  "PD_NPC_Zeb_Guardian_T21_Zebian_Blood_Curator": "PD_NPC_Zeb_Guardian_T21_Zebian_Blood_Curator",
  "PD_NPC_Zeb_Guardian_T21_Zebian_Manflayer": "PD_NPC_Zeb_Guardian_T21_Zebian_Manflayer",
  "PD_NPC_Zeb_Guardian_T33_Priest_of_Zeb": "PD_NPC_Zeb_Guardian_T33_Priest_of_Zeb",
  "PD_NPC_Zeb_Guardian_T40_Valet_of_the_Chamber": "PD_NPC_Zeb_Guardian_T40_Valet_of_the_Chamber",
  "PD_NPC_Zeb_Guardian_T40_Warden_of_the_Hall": "PD_NPC_Zeb_Guardian_T40_Warden_of_the_Hall",
  "PD_NPC_Zeb_Overseer_T32_Rivulet_Alchemist": "PD_NPC_Zeb_Overseer_T32_Rivulet_Alchemist",
  "PD_NPC_Zeb_Overseer_T35_Herald_of_Zeb": "PD_NPC_Zeb_Overseer_T35_Herald_of_Zeb",
  "PD_NPC_Zeb_Overseer_T36_Maggotridden_Host": "PD_NPC_Zeb_Overseer_T36_Maggotridden_Host",
  "PD_NPC_Zeb_Warrior_T20_Culler_of_the_Weak": "PD_NPC_Zeb_Warrior_T20_Culler_of_the_Weak",
  "PD_NPC_Zeb_Warrior_T20_Wasp_Whisperer": "PD_NPC_Zeb_Warrior_T20_Wasp_Whisperer",
  "PD_NPC_Zeb_Warrior_T22_Zebian_Messenger": "PD_NPC_Zeb_Warrior_T22_Zebian_Messenger",
  "PD_NPC_Zeb_Warrior_T24_Zebian_Eye_Collector": "PD_NPC_Zeb_Warrior_T24_Zebian_Eye_Collector",
  "PD_NPC_Zeb_Warrior_T27_Frenzied_Feeder": "PD_NPC_Zeb_Warrior_T27_Frenzied_Feeder",
  "PD_NPC_Zeb_Warrior_T32_Hallboy": "PD_NPC_Zeb_Warrior_T32_Hallboy",
  "PD_NPC_Zeb_Warrior_T33_Rivulet_Courier": "PD_NPC_Zeb_Warrior_T33_Rivulet_Courier",
  "PD_NPC_Zeb_Warrior_T34_Enthralled_Host": "PD_NPC_Zeb_Warrior_T34_Enthralled_Host",
  "PD_NPC_Zeb_Warrior_T36_Hoggish_Cultist": "PD_NPC_Zeb_Warrior_T36_Hoggish_Cultist",
  "PD_NPC_Zeb_Warrior_T37_Piggish_Cultist": "PD_NPC_Zeb_Warrior_T37_Piggish_Cultist",
  "PD_NPC_Zeb_Warrior_T37_Swinish_Cultist": "PD_NPC_Zeb_Warrior_T37_Swinish_Cultist",
  "PD_NPC_Zeb_Doctor_T40_Spider": "PD_NPC_Zeb_Doctor_T40_Spider",
  "PD_NPC_Zeb_Doctor_T42_Assistant_Zanette": "PD_NPC_Zeb_Doctor_T42_Assistant_Zanette",
  "PD_NPC_Zeb_Doctor_T42_The_Poisoner": "PD_NPC_Zeb_Doctor_T42_The_Poisoner",
  "PD_NPC_Zeb_Doctor_T42_Tick": "PD_NPC_Zeb_Doctor_T42_Tick",
  "PD_NPC_Zeb_Doctor_T45_Chief_of_the_Oath": "PD_NPC_Zeb_Doctor_T45_Chief_of_the_Oath",
  "PD_NPC_Zeb_Doctor_T45_Leader_of_Chants": "PD_NPC_Zeb_Doctor_T45_Leader_of_Chants",
  "PD_NPC_Zeb_Doctor_T49_The_Temple_Dispencer": "PD_NPC_Zeb_Doctor_T49_The_Temple_Dispencer",
  "PD_NPC_Zeb_Doctor_T49_The_Temple_Larderer": "PD_NPC_Zeb_Doctor_T49_The_Temple_Larderer",
  "PD_NPC_Zeb_Doctor_T49_The_Temple_Pantler": "PD_NPC_Zeb_Doctor_T49_The_Temple_Pantler",
  "PD_NPC_Zeb_Doctor_T52_Ambolons_Serf": "PD_NPC_Zeb_Doctor_T52_Ambolons_Serf",
  "PD_NPC_Zeb_Doctor_T52_Namiross_Pet": "PD_NPC_Zeb_Doctor_T52_Namiross_Pet",
  "PD_NPC_Zeb_Doctor_T54_The_Mouth_of_Magalast": "PD_NPC_Zeb_Doctor_T54_The_Mouth_of_Magalast",
  "PD_NPC_Zeb_Guardian_T42_Boarmaster_Gan": "PD_NPC_Zeb_Guardian_T42_Boarmaster_Gan",
  "PD_NPC_Zeb_Guardian_T42_Gatekeeper_Montel": "PD_NPC_Zeb_Guardian_T42_Gatekeeper_Montel",
  "PD_NPC_Zeb_Guardian_T42_Master_Gryllus": "PD_NPC_Zeb_Guardian_T42_Master_Gryllus",
  "PD_NPC_Zeb_Guardian_T42_Master_Phyrrhocoris": "PD_NPC_Zeb_Guardian_T42_Master_Phyrrhocoris",
  "PD_NPC_Zeb_Guardian_T42_Mistress_Elytra": "PD_NPC_Zeb_Guardian_T42_Mistress_Elytra",
  "PD_NPC_Zeb_Guardian_T42_Mite": "PD_NPC_Zeb_Guardian_T42_Mite",
  "PD_NPC_Zeb_Guardian_T42_Roach": "PD_NPC_Zeb_Guardian_T42_Roach",
  "PD_NPC_Zeb_Guardian_T42_Scudder_Apolline": "PD_NPC_Zeb_Guardian_T42_Scudder_Apolline",
  "PD_NPC_Zeb_Guardian_T42_The_Fete_Mistress": "PD_NPC_Zeb_Guardian_T42_The_Fete_Mistress",
  "PD_NPC_Zeb_Guardian_T42_The_Temple_Butler": "PD_NPC_Zeb_Guardian_T42_The_Temple_Butler",
  "PD_NPC_Zeb_Guardian_T45_Pellipis_Pet": "PD_NPC_Zeb_Guardian_T45_Pellipis_Pet",
  "PD_NPC_Zeb_Guardian_T46_Kabadas_Craving": "PD_NPC_Zeb_Guardian_T46_Kabadas_Craving",
  "PD_NPC_Zeb_Guardian_T47_Diralisens_Cutler": "PD_NPC_Zeb_Guardian_T47_Diralisens_Cutler",
  "PD_NPC_Zeb_Guardian_T47_Plisons_Wetboy": "PD_NPC_Zeb_Guardian_T47_Plisons_Wetboy",
  "PD_NPC_Zeb_Guardian_T49_Webtender_Kaira": "PD_NPC_Zeb_Guardian_T49_Webtender_Kaira",
  "PD_NPC_Zeb_Guardian_T50_Force_Feeder_Oran": "PD_NPC_Zeb_Guardian_T50_Force_Feeder_Oran",
  "PD_NPC_Zeb_Guardian_T50_Steward_of_Ambolon": "PD_NPC_Zeb_Guardian_T50_Steward_of_Ambolon",
  "PD_NPC_Zeb_Guardian_T50_Supplicant_Andrena": "PD_NPC_Zeb_Guardian_T50_Supplicant_Andrena",
  "PD_NPC_Zeb_Guardian_T50_The_Roach_Tender": "PD_NPC_Zeb_Guardian_T50_The_Roach_Tender",
  "PD_NPC_Zeb_Guardian_T52_Licanens_Waft": "PD_NPC_Zeb_Guardian_T52_Licanens_Waft",
  "PD_NPC_Zeb_Guardian_T52_Wicked_Liturgist": "PD_NPC_Zeb_Guardian_T52_Wicked_Liturgist",
  "PD_NPC_Zeb_Guardian_T54_Force_Feeder_Jeremy": "PD_NPC_Zeb_Guardian_T54_Force_Feeder_Jeremy",
  "PD_NPC_Zeb_Guardian_T54_Kabadas_Current_Fare": "PD_NPC_Zeb_Guardian_T54_Kabadas_Current_Fare",
  "PD_NPC_Zeb_Guardian_T54_Supplicant_Danuria": "PD_NPC_Zeb_Guardian_T54_Supplicant_Danuria",
  "PD_NPC_Zeb_Guardian_T54_Supplicant_Trigona": "PD_NPC_Zeb_Guardian_T54_Supplicant_Trigona",
  "PD_NPC_Zeb_Overseer_T42_Master_Arcturus": "PD_NPC_Zeb_Overseer_T42_Master_Arcturus",
  "PD_NPC_Zeb_Overseer_T42_Master_of_Fetes": "PD_NPC_Zeb_Overseer_T42_Master_of_Fetes",
  "PD_NPC_Zeb_Overseer_T42_Wolfmaster_Bon": "PD_NPC_Zeb_Overseer_T42_Wolfmaster_Bon",
  "PD_NPC_Zeb_Overseer_T48_Hivetender_Cordulia": "PD_NPC_Zeb_Overseer_T48_Hivetender_Cordulia",
  "PD_NPC_Zeb_Overseer_T48_Hivetender_Ladonia": "PD_NPC_Zeb_Overseer_T48_Hivetender_Ladonia",
  "PD_NPC_Zeb_Overseer_T50_Hivetender_Rhyssa": "PD_NPC_Zeb_Overseer_T50_Hivetender_Rhyssa",
  "PD_NPC_Zeb_Overseer_T50_The_Feeding_Master": "PD_NPC_Zeb_Overseer_T50_The_Feeding_Master",
  "PD_NPC_Zeb_Overseer_T50_The_Hellion_Feeder": "PD_NPC_Zeb_Overseer_T50_The_Hellion_Feeder",
  "PD_NPC_Zeb_Overseer_T50_The_Imp_Feeder": "PD_NPC_Zeb_Overseer_T50_The_Imp_Feeder",
  "PD_NPC_Zeb_Overseer_T52_Webtender_Nephila": "PD_NPC_Zeb_Overseer_T52_Webtender_Nephila",
  "PD_NPC_Zeb_Overseer_T54_The_Tender_Roach": "PD_NPC_Zeb_Overseer_T54_The_Tender_Roach",
  "PD_NPC_Zeb_Warrior_T40_Flea": "PD_NPC_Zeb_Warrior_T40_Flea",
  "PD_NPC_Zeb_Warrior_T40_Moth": "PD_NPC_Zeb_Warrior_T40_Moth",
  "PD_NPC_Zeb_Warrior_T40_Soaker_Sharice": "PD_NPC_Zeb_Warrior_T40_Soaker_Sharice",
  "PD_NPC_Zeb_Warrior_T40_Tanner_Margarida": "PD_NPC_Zeb_Warrior_T40_Tanner_Margarida",
  "PD_NPC_Zeb_Warrior_T42_Butcher_Jehan": "PD_NPC_Zeb_Warrior_T42_Butcher_Jehan",
  "PD_NPC_Zeb_Warrior_T42_Skinner_Amabelle": "PD_NPC_Zeb_Warrior_T42_Skinner_Amabelle",
  "PD_NPC_Zeb_Warrior_T42_The_Pickler": "PD_NPC_Zeb_Warrior_T42_The_Pickler",
  "PD_NPC_Zeb_Warrior_T46_Orgosils_Favorite_Victim": "PD_NPC_Zeb_Warrior_T46_Orgosils_Favorite_Victim",
  "PD_NPC_Zeb_Warrior_T46_Sorosmas_Cremator": "PD_NPC_Zeb_Warrior_T46_Sorosmas_Cremator",
  "PD_NPC_Zeb_Warrior_T47_Holastris_Strategist": "PD_NPC_Zeb_Warrior_T47_Holastris_Strategist",
  "PD_NPC_Zeb_Warrior_T48_Kipokiss_Delight": "PD_NPC_Zeb_Warrior_T48_Kipokiss_Delight",
  "PD_NPC_Zeb_Warrior_T48_Webtender_Rhene": "PD_NPC_Zeb_Warrior_T48_Webtender_Rhene",
  "PD_NPC_Zeb_Warrior_T50_The_Ichorlicker": "PD_NPC_Zeb_Warrior_T50_The_Ichorlicker",
  "PD_NPC_Zeb_Warrior_T50_The_Waspmaster": "PD_NPC_Zeb_Warrior_T50_The_Waspmaster",
  "PD_NPC_Zeb_Warrior_T50_The_Will_of_Holastri": "PD_NPC_Zeb_Warrior_T50_The_Will_of_Holastri",
  "PD_NPC_Zeb_Warrior_T52_Lamalons_Shadow": "PD_NPC_Zeb_Warrior_T52_Lamalons_Shadow",
  "PD_NPC_Zeb_Warrior_T52_Magalasts_Craving": "PD_NPC_Zeb_Warrior_T52_Magalasts_Craving",
  "PD_NPC_Zeb_Warrior_T52_Zagalos_Nag": "PD_NPC_Zeb_Warrior_T52_Zagalos_Nag",
  "PD_NPC_Zeb_Warrior_T54_Diralisens_Desire": "PD_NPC_Zeb_Warrior_T54_Diralisens_Desire",
  "PD_NPC_Zeb_Warrior_T54_Master_of_Flies": "PD_NPC_Zeb_Warrior_T54_Master_of_Flies",
  "PD_NPC_Zeb_Warrior_T54_Master_of_Wax": "PD_NPC_Zeb_Warrior_T54_Master_of_Wax",
  "PD_NPC_Zeb_Warrior_T54_The_Temple_Cellarer": "PD_NPC_Zeb_Warrior_T54_The_Temple_Cellarer",
  "PD_NPC_Demon_Duke": "PD_NPC_Demon_Duke",
  "PD_NPC_Demon_Hellion_T24": "PD_NPC_Demon_Hellion_T24",
  "PD_NPC_Demon_Hellion_T30": "PD_NPC_Demon_Hellion_T30",
  "PD_NPC_Demon_Hellion_T42": "PD_NPC_Demon_Hellion_T42",
  "PD_NPC_Demon_Imp_T14": "PD_NPC_Demon_Imp_T14",
  "PD_NPC_Demon_Imp_T21": "PD_NPC_Demon_Imp_T21",
  "PD_NPC_Demon_Imp_T21_summon": "PD_NPC_Demon_Imp_T21_summon",
  "PD_NPC_Demon_Imp_T31": "PD_NPC_Demon_Imp_T31",
  "PD_NPC_Demon_Imp_T35_summon": "PD_NPC_Demon_Imp_T35_summon",
  "PD_NPC_Demon_Imp_T41": "PD_NPC_Demon_Imp_T41",
  "PD_NPC_Demon_Hellion_T26_Inspector_of_Zeb": "PD_NPC_Demon_Hellion_T26_Inspector_of_Zeb",
  "PD_NPC_Demon_Hellion_T40_Inspector_of_Excrements": "PD_NPC_Demon_Hellion_T40_Inspector_of_Excrements",
  "PD_NPC_Demon_Hellion_T40_Servant_of_Dorak": "PD_NPC_Demon_Hellion_T40_Servant_of_Dorak",
  "PD_NPC_Demon_Hellion_T42_Roaming_Glutton": "PD_NPC_Demon_Hellion_T42_Roaming_Glutton",
  "PD_NPC_Demon_Hellion_T42_Servant_of_Orgosil": "PD_NPC_Demon_Hellion_T42_Servant_of_Orgosil",
  "PD_NPC_Demon_Imp_T23_Infested_Apparition": "PD_NPC_Demon_Imp_T23_Infested_Apparition",
  "PD_NPC_Demon_Imp_T24_Excrement_Collector": "PD_NPC_Demon_Imp_T24_Excrement_Collector",
  "PD_NPC_Demon_Imp_T38_Eye_of_Zeb": "PD_NPC_Demon_Imp_T38_Eye_of_Zeb",
  "PD_NPC_Demon_Imp_T38_Shadow_of_Gluttony": "PD_NPC_Demon_Imp_T38_Shadow_of_Gluttony",
  "PD_NPC_Demon_Imp_T38_Spirit_of_the_Hive": "PD_NPC_Demon_Imp_T38_Spirit_of_the_Hive",
  "PD_NPC_Demon_Imp_T38_Spirit_of_the_Mound": "PD_NPC_Demon_Imp_T38_Spirit_of_the_Mound",
  "PD_NPC_Demon_Hellion_T42_Emmissary_of_Amatia": "PD_NPC_Demon_Hellion_T42_Emmissary_of_Amatia",
  "PD_NPC_Demon_Hellion_T42_Tainted_Glutton": "PD_NPC_Demon_Hellion_T42_Tainted_Glutton",
  "PD_NPC_Demon_Hellion_T42_The_Eye_of_Diralisen": "PD_NPC_Demon_Hellion_T42_The_Eye_of_Diralisen",
  "PD_NPC_Demon_Hellion_T52_Ambolons_Left_Hand": "PD_NPC_Demon_Hellion_T52_Ambolons_Left_Hand",
  "PD_NPC_Demon_Hellion_T52_Ambolons_Right_Hand": "PD_NPC_Demon_Hellion_T52_Ambolons_Right_Hand",
  "PD_NPC_Demon_Hellion_T52_Bulimix": "PD_NPC_Demon_Hellion_T52_Bulimix",
  "PD_NPC_Demon_Hellion_T52_Hyperphagix": "PD_NPC_Demon_Hellion_T52_Hyperphagix",
  "PD_NPC_Demon_Hellion_T52_The_Tint_of_Gluttony": "PD_NPC_Demon_Hellion_T52_The_Tint_of_Gluttony",
  "PD_NPC_Demon_Hellion_T54_Lamolons_Feeder": "PD_NPC_Demon_Hellion_T54_Lamolons_Feeder",
  "PD_NPC_Demon_Hellion_T54_The_Lords_Emmissary": "PD_NPC_Demon_Hellion_T54_The_Lords_Emmissary",
  "PD_NPC_Demon_Imp_T42_Doraks_Valet": "PD_NPC_Demon_Imp_T42_Doraks_Valet",
  "PD_NPC_Demon_Imp_T42_The_Eye_of_Pellipis": "PD_NPC_Demon_Imp_T42_The_Eye_of_Pellipis",
  "PD_NPC_Demon_Imp_T50_Sycophant_to_Lycanen": "PD_NPC_Demon_Imp_T50_Sycophant_to_Lycanen",
  "PD_NPC_Demon_Imp_T50_Sycophant_to_Magalast": "PD_NPC_Demon_Imp_T50_Sycophant_to_Magalast",
  "PD_NPC_Willowisp_T90": "PD_NPC_Willowisp_T90",
  "PD_NPC_Inq_Captain_T10": "PD_NPC_Inq_Captain_T10",
  "PD_NPC_Inq_Captain_T16": "PD_NPC_Inq_Captain_T16",
  "PD_NPC_Inq_Captain_T22": "PD_NPC_Inq_Captain_T22",
  "PD_NPC_Inq_Caster_T15": "PD_NPC_Inq_Caster_T15",
  "PD_NPC_Inq_Caster_T21": "PD_NPC_Inq_Caster_T21",
  "PD_NPC_Inq_Caster_T8": "PD_NPC_Inq_Caster_T8",
  "PD_NPC_Inq_Cleric_T12": "PD_NPC_Inq_Cleric_T12",
  "PD_NPC_Inq_Cleric_T18": "PD_NPC_Inq_Cleric_T18",
  "PD_NPC_Inq_Cleric_T7": "PD_NPC_Inq_Cleric_T7",
  "PD_NPC_Inq_Scout_T10": "PD_NPC_Inq_Scout_T10",
  "PD_NPC_Inq_Scout_T16": "PD_NPC_Inq_Scout_T16",
  "PD_NPC_Inq_Scout_T6": "PD_NPC_Inq_Scout_T6",
  "PD_NPC_Inq_Tank_T13": "PD_NPC_Inq_Tank_T13",
  "PD_NPC_Inq_Tank_T19": "PD_NPC_Inq_Tank_T19",
  "PD_NPC_Inq_Tank_T9": "PD_NPC_Inq_Tank_T9",
  "PD_NPC_Inq_Captain_T15_Manic_Torturer": "PD_NPC_Inq_Captain_T15_Manic_Torturer",
  "PD_NPC_Inq_Captain_T18_Enraged_Interrogator": "PD_NPC_Inq_Captain_T18_Enraged_Interrogator",
  "PD_NPC_Inq_Captain_T18_Examiner_of_Signs": "PD_NPC_Inq_Captain_T18_Examiner_of_Signs",
  "PD_NPC_Inq_Captain_T18_Watchful_Interrogator": "PD_NPC_Inq_Captain_T18_Watchful_Interrogator",
  "PD_NPC_Inq_Captain_T27_Attentive_Torturer": "PD_NPC_Inq_Captain_T27_Attentive_Torturer",
  "PD_NPC_Inq_Caster_T14_Canoness_Regular": "PD_NPC_Inq_Caster_T14_Canoness_Regular",
  "PD_NPC_Inq_Caster_T14_Exorcist_Cantor": "PD_NPC_Inq_Caster_T14_Exorcist_Cantor",
  "PD_NPC_Inq_Caster_T16_Entranced_Exorcist": "PD_NPC_Inq_Caster_T16_Entranced_Exorcist",
  "PD_NPC_Inq_Caster_T18_Candle_Holder": "PD_NPC_Inq_Caster_T18_Candle_Holder",
  "PD_NPC_Inq_Caster_T18_Canon_Regular": "PD_NPC_Inq_Caster_T18_Canon_Regular",
  "PD_NPC_Inq_Caster_T18_Discalced_Cantor": "PD_NPC_Inq_Caster_T18_Discalced_Cantor",
  "PD_NPC_Inq_Caster_T27_Lector_illuminare": "PD_NPC_Inq_Caster_T27_Lector_illuminare",
  "PD_NPC_Inq_Cleric_T17_Examiner_of_Truth": "PD_NPC_Inq_Cleric_T17_Examiner_of_Truth",
  "PD_NPC_Inq_Cleric_T17_Inquisitor_ferox": "PD_NPC_Inq_Cleric_T17_Inquisitor_ferox",
  "PD_NPC_Inq_Cleric_T17_Lector_de_sermo": "PD_NPC_Inq_Cleric_T17_Lector_de_sermo",
  "PD_NPC_Inq_Cleric_T17_Lector_secretorum": "PD_NPC_Inq_Cleric_T17_Lector_secretorum",
  "PD_NPC_Inq_Scout_T15_Inquisitor_Veritatis": "PD_NPC_Inq_Scout_T15_Inquisitor_Veritatis",
  "PD_NPC_Inq_Scout_T25_Inquisitor_fortis": "PD_NPC_Inq_Scout_T25_Inquisitor_fortis",
  "PD_NPC_Inq_Scout_T26_Examiner_of_Vows": "PD_NPC_Inq_Scout_T26_Examiner_of_Vows",
  "PD_NPC_Inq_Tank_T15_Inquisitor_pura": "PD_NPC_Inq_Tank_T15_Inquisitor_pura",
  "PD_NPC_Inq_Tank_T15_Wary_Ostiary": "PD_NPC_Inq_Tank_T15_Wary_Ostiary",
  "PD_NPC_Inq_Tank_T17_Examiner_of_Life": "PD_NPC_Inq_Tank_T17_Examiner_of_Life",
  "PD_NPC_Inq_Tank_T18_Examiner_of_Death": "PD_NPC_Inq_Tank_T18_Examiner_of_Death",
  "PD_NPC_Inq_Tank_T18_Examiner_of_Tests": "PD_NPC_Inq_Tank_T18_Examiner_of_Tests",
  "PD_NPC_Inq_Captain_T22_Inquisitor_Peter_de_Salias": "PD_NPC_Inq_Captain_T22_Inquisitor_Peter_de_Salias",
  "PD_NPC_Inq_Captain_T22_Ostraciser_Adelin": "PD_NPC_Inq_Captain_T22_Ostraciser_Adelin",
  "PD_NPC_Inq_Captain_T22_Persecutor_Oldaric": "PD_NPC_Inq_Captain_T22_Persecutor_Oldaric",
  "PD_NPC_LostSoul_T16": "PD_NPC_LostSoul_T16",
  "PD_NPC_LostSoul_T22": "PD_NPC_LostSoul_T22",
  "PD_NPC_LostSoul_T32": "PD_NPC_LostSoul_T32",
  "PD_NPC_LostSoul_T25_Somber_Visitant": "PD_NPC_LostSoul_T25_Somber_Visitant",
  "PD_NPC_LostSoul_T26_Cruel_Visitant": "PD_NPC_LostSoul_T26_Cruel_Visitant",
  "PD_NPC_LostSoul_T26_Dismal_Visitant": "PD_NPC_LostSoul_T26_Dismal_Visitant",
  "PD_NPC_LostSoul_T26_Gloomy_Visitant": "PD_NPC_LostSoul_T26_Gloomy_Visitant",
  "PD_NPC_LostSoul_T26_Onerous_Visitant": "PD_NPC_LostSoul_T26_Onerous_Visitant",
  "PD_NPC_LostSoul_T26_Spiteful_Visitant": "PD_NPC_LostSoul_T26_Spiteful_Visitant",
  "PD_NPC_LostSoul_T27_Dark_Visitant": "PD_NPC_LostSoul_T27_Dark_Visitant",
  "PD_NPC_LostSoul_T34_Erratic_Visitation": "PD_NPC_LostSoul_T34_Erratic_Visitation",
  "PD_NPC_LostSoul_T34_Silent_Visitant": "PD_NPC_LostSoul_T34_Silent_Visitant",
  "PD_NPC_LostSoul_T35_Fetid_Visitation": "PD_NPC_LostSoul_T35_Fetid_Visitation",
  "PD_NPC_LostSoul_T35_Vile_Visitant": "PD_NPC_LostSoul_T35_Vile_Visitant",
  "PD_NPC_LostSoul_T36_Cold_Visitant": "PD_NPC_LostSoul_T36_Cold_Visitant",
  "PD_NPC_LostSoul_T36_Intrusive_Visitant": "PD_NPC_LostSoul_T36_Intrusive_Visitant",
  "PD_NPC_LostSoul_T37_Bleak_Visitant": "PD_NPC_LostSoul_T37_Bleak_Visitant",
  "PD_NPC_Griffon": "PD_NPC_Griffon",
  "PD_NPC_Wyvern_Adult_Woods": "PD_NPC_Wyvern_Adult_Woods"
}